{
  "$schema": "https://raw.githubusercontent.com/googleapis/release-please/main/schemas/config.json",
  "changelog-sections": [
    {
      "type": "feat",
      "section": "Features",
      "hidden": false
    },
    {
      "type": "feature",
      "section": "Features",
      "hidden": false
    },
    {
      "type": "fix",
      "section": "Bug Fixes",
      "hidden": false
    },
    {
      "type": "perf",
      "section": "Performance Improvements",
      "hidden": false
    },
    {
      "type": "revert",
      "section": "Reverts",
      "hidden": false
    },
    {
      "type": "docs",
      "section": "Documentation",
      "hidden": false
    },
    {
      "type": "style",
      "section": "Styles",
      "hidden": false
    },
    {
      "type": "chore",
      "section": "Miscellaneous",
      "hidden": false
    },
    {
      "type": "misc",
      "section": "Miscellaneous",
      "hidden": false
    },
    {
      "type": "refactor",
      "section": "Code Refactoring",
      "hidden": false
    },
    {
      "type": "test",
      "section": "Tests",
      "hidden": false
    },
    {
      "type": "build",
      "section": "Build System",
      "hidden": false
    },
    {
      "type": "ci",
      "section": "Continuous Integration",
      "hidden": false
    },
    {
      "type": "deps",
      "section": "Dependencies",
      "hidden": false
    }
  ],
  "include-component-in-tag": false,
  "pull-request-title-pattern": "chore: Release ${version}",
  "packages": {
    ".": {
      "release-type": "python",
      "extra-files": [
        {
          "type": "toml",
          "path": "uv.lock",
          "jsonpath": "$.package[?(@.name.value=='librechat_exporter')].version"
        },
        {
          "type": "generic",
          "path": "README.md"
        }
      ]
    }
  }
}